tbats/__init__.py
tbats/abstract/ArrayHelper.py
tbats/abstract/Case.py
tbats/abstract/ComponentMatrix.py
tbats/abstract/Components.py
tbats/abstract/Context.py
tbats/abstract/ContextInterface.py
tbats/abstract/Estimator.py
tbats/abstract/MatrixBuilder.py
tbats/abstract/MatrixBuilderCache.py
tbats/abstract/MatrixBuilderInterface.py
tbats/abstract/Model.py
tbats/abstract/ModelParams.py
tbats/abstract/ParamsOptimizer.py
tbats/abstract/SeedFinder.py
tbats/abstract/__init__.py
tbats/bats/BATS.py
tbats/bats/Case.py
tbats/bats/Components.py
tbats/bats/Context.py
tbats/bats/MatrixBuilder.py
tbats/bats/Model.py
tbats/bats/ModelParams.py
tbats/bats/ParamsOptimizer.py
tbats/bats/SeedFinder.py
tbats/bats/__init__.py
tbats/error/BatsException.py
tbats/error/BatsWarning.py
tbats/error/ExceptionHandler.py
tbats/error/InputArgsException.py
tbats/error/InputArgsWarning.py
tbats/error/ModelWarning.py
tbats/error/__init__.py
tbats/tbats/Case.py
tbats/tbats/Components.py
tbats/tbats/Context.py
tbats/tbats/HarmonicsChoosingStrategy.py
tbats/tbats/MatrixBuilder.py
tbats/tbats/Model.py
tbats/tbats/ModelParams.py
tbats/tbats/ParamsOptimizer.py
tbats/tbats/SeedFinder.py
tbats/tbats/TBATS.py
tbats/tbats/__init__.py
tbats/transformation/BoxCox.py
tbats/transformation/Guerrero.py
tbats/transformation/__init__.py
tbats-1.1.3.dist-info/AUTHORS.txt
tbats-1.1.3.dist-info/LICENSE
tbats-1.1.3.dist-info/METADATA
tbats-1.1.3.dist-info/WHEEL
tbats-1.1.3.dist-info/top_level.txt
tbats-1.1.3.dist-info/RECORD
