Metadata-Version: 2.1
Name: tbats
Version: 1.1.3
Summary: BATS and TBATS for time series forecasting
Home-page: https://github.com/intive-DataScience/tbats
Author: Grzegorz Skorupa (intive)
Author-email: grzegorz.skorupa@intive.com
License: MIT License
Classifier: Programming Language :: Python :: 3
Classifier: License :: OSI Approved :: MIT License
Classifier: Operating System :: OS Independent
Provides-Extra: dev
License-File: LICENSE
License-File: AUTHORS.txt
